mono/__init__.py
mono/api/__init__.py
mono/api/base_api.py
mono/api/directpay.py
mono/api/errors.py
mono/api/misc.py
mono/api/mono_account.py
mono/api/mono_user.py
mono/api/mono_wallet.py
mono/api/unlink_acc.py
mono/api/utils.py
mono/api/x.py
tests/__init__.py
tests/test_directpay.py
tests/test_misc.py
tests/test_mono_account.py
tests/test_mono_user.py
tests/test_wallet.py
monopy-1.0.3.dist-info/LICENSE
monopy-1.0.3.dist-info/METADATA
monopy-1.0.3.dist-info/WHEEL
monopy-1.0.3.dist-info/top_level.txt
monopy-1.0.3.dist-info/RECORD
