Metadata-Version: 2.1
Name: monopy
Version: 1.0.3
Summary: a python wrapper for the Mono API
Home-page: https://github.com/iameo/monopy
Author: Emmanuel Okwudike
Author-email: okwudike.emmanuel@gmail.com
License: MIT
Project-URL: Bug Tracker, https://github.com/iameo/monopy/issues
Keywords: monopy pywrapper fintech api monong
Platform: UNKNOWN
Classifier: Programming Language :: Python :: 3
Classifier: License :: OSI Approved :: MIT License
Classifier: Operating System :: OS Independent
Requires-Python: >=3.6
License-File: LICENSE
Requires-Dist: requests
